NOKIRY/__init__.py
NOKIRY/example.py
nokiry-0.0.1.dist-info/LICENSE
nokiry-0.0.1.dist-info/METADATA
nokiry-0.0.1.dist-info/WHEEL
nokiry-0.0.1.dist-info/top_level.txt
nokiry-0.0.1.dist-info/RECORD
