Metadata-Version: 2.1
Name: nokiry
Version: 0.0.1
Summary: great for math
Home-page: 
Author: Donal
Author-email: adaridonalrahul@gmail.com
Project-URL: Bug Tracker, https://github.com/pypa/sampleproject/issues
Classifier: Programming Language :: Python :: 3
Classifier: License :: OSI Approved :: MIT License
Classifier: Operating System :: OS Independent
Requires-Python: >=3.6
License-File: LICENSE
